{
  "name": "Ageless Automaton",
  "rarity": "Rare",
  "type": "Creature",
  "subtypes": [
    "Dwemer"
  ],
  "cost": 4,
  "power": 2,
  "health": 5,
  "set": {
    "name": "Core Set",
    "id": "cs"
  },
  "collectible": true,
  "soulSummon": 100,
  "soulTrap": 20,
  "text": "When Ageless Automaton attacks a Guard, it gains +3/+0 and Breakthrough until end of turn.",
  "attributes": [
    "Neutral"
  ],
  "keywords": [
    "Breakthrough",
    "Guard"
  ],
  "unique": false,
  "imageUrl": "https://www.legends-decks.com/img_cards/agelessautomaton.png",
  "id": "897c6203-3358-50c0-9202-751e9b189819",
  "code": "ai"
}
