{
  "name": "Bruma Armorer",
  "rarity": "Rare",
  "type": "Creature",
  "subtypes": [
    "Imperial"
  ],
  "cost": 3,
  "power": 2,
  "health": 2,
  "set": {
    "name": "Core Set",
    "id": "cs"
  },
  "collectible": true,
  "soulSummon": 100,
  "soulTrap": 20,
  "text": "When you summon another, give it +0/+2.",
  "attributes": [
    "Endurance"
  ],
  "keywords": [],
  "unique": false,
  "imageUrl": "https://images.elderscrollslegends.io/cs/bruma_armorer.png",
  "id": "d2777f2d-2065-5882-b9e8-4a63e7e22336",
  "code": "cw"
}
