{
  "name": "Champion of the Arena",
  "rarity": "Epic",
  "type": "Creature",
  "subtypes": [
    "Orc",
    "Vampire"
  ],
  "cost": 7,
  "power": 4,
  "health": 8,
  "set": {
    "name": "Monthly Rewards",
    "id": "mr"
  },
  "collectible": true,
  "soulSummon": 400,
  "soulTrap": 100,
  "text": "Breakthrough Summon: Battle an enemy creature",
  "attributes": [
    "Strength",
    "Endurance"
  ],
  "keywords": [
    "Breakthrough"
  ],
  "unique": false,
  "imageUrl": "https://www.legends-decks.com/img_cards/championofthearena.png",
  "id": "8d0309c1-e74d-5d69-ae6e-cc5eb37302a5",
  "code": "yJ"
}
