{
  "name": "Gearwork Spider",
  "rarity": "Common",
  "type": "Creature",
  "subtypes": [
    "Dwemer"
  ],
  "cost": 1,
  "power": 1,
  "health": 1,
  "set": {
    "name": "Return to Clockwork City",
    "id": "rcc"
  },
  "collectible": true,
  "soulSummon": 50,
  "soulTrap": 5,
  "text": "Summon: Summon all Gearwork Spiders in your discard pile.",
  "attributes": [
    "Neutral"
  ],
  "keywords": [
    "Prophecy",
    "Guard"
  ],
  "unique": false,
  "imageUrl": "https://images.elderscrollslegends.io/rcc/gearwork_spider.png",
  "id": "959191c8-8c33-5168-a614-36df31dbe109",
  "code": "gU"
}
