{
  "name": "Gray Viper Brigand",
  "rarity": "Epic",
  "type": "Creature",
  "subtypes": [
    "Wood Elf"
  ],
  "cost": 3,
  "power": 3,
  "health": 4,
  "set": {
    "name": "Alliance War",
    "id": "aw"
  },
  "collectible": true,
  "soulSummon": 400,
  "soulTrap": 100,
  "text": "Summon: Draw a card for each Gray Viper Brigand in your discard pile.",
  "attributes": [
    "Willpower"
  ],
  "keywords": [],
  "unique": false,
  "imageUrl": "https://www.legends-decks.com/img_cards/grayviperbrigand.png",
  "id": "0bd21d9f-694a-5df2-9ed8-a85bd923bd2e",
  "code": "uA"
}
