{
  "name": "Halls of Colossus",
  "rarity": "Legendary",
  "type": "Support",
  "subtypes": [],
  "cost": 12,
  "power": -1,
  "health": -1,
  "set": {
    "name": "Moons of Elsweyr",
    "id": "moe"
  },
  "collectible": false,
  "soulSummon": -1,
  "soulTrap": -1,
  "text": "Uses: 3. Activate: Summon a non-Unique Dragon of your choice from your deck.",
  "attributes": [
    "Willpower"
  ],
  "keywords": [],
  "unique": true,
  "imageUrl": "https://images.elderscrollslegends.io/moe/halls_of_colossus.png",
  "id": "28212cb8-76b4-57db-be0f-34f2c5f00319",
  "code": "__"
}
