{
  "name": "Harmony",
  "rarity": "Rare",
  "type": "Action",
  "subtypes": [],
  "cost": 2,
  "power": -1,
  "health": -1,
  "set": {
    "name": "FrostSpark Collection",
    "id": "fsc"
  },
  "collectible": true,
  "soulSummon": 100,
  "soulTrap": 20,
  "text": "Prophecy. Give all enemy creatures -2/-0 until the start of your turn.",
  "attributes": [
    "Willpower"
  ],
  "keywords": [
    "Prophecy"
  ],
  "unique": false,
  "imageUrl": "https://images.elderscrollslegends.io/fsc/harmony.png",
  "id": "6c30b355-13ad-58eb-a87d-7dbdb97e0dad",
  "code": "hQ",
  "isAlt": false
}
